MANIFEST.in
README.md
setup.cfg
setup.py
django_b64_img/__init__.py
django_b64_img/fields.py
django_b64_img.egg-info/PKG-INFO
django_b64_img.egg-info/SOURCES.txt
django_b64_img.egg-info/dependency_links.txt
django_b64_img.egg-info/top_level.txt