Metadata-Version: 1.1
Name: django-b64-img
Version: 1.1
Summary: Enter html description here
Home-page: UNKNOWN
Author: golchen chempo
Author-email: golchenchempo@gmail.com
License: License
Platform: UNKNOWN
Classifier: Environment :: Web Environment
Classifier: Framework :: Django
Classifier: Intended Audience :: Developers
Classifier: Operating System :: OS Independent
Classifier: Programming Language :: Python
Classifier: Topic :: Internet :: WWW/HTTP
Classifier: Topic :: Internet :: WWW/HTTP :: Dynamic Content
